[
   {
    "photo1": "https://upload.wikimedia.org/wikipedia/en/thumb/5/53/Arsenal_FC.svg/1200px-Arsenal_FC.svg.png",
    "name1": "Arsenal",
    "photo2": "https://upload.wikimedia.org/wikipedia/fr/thumb/8/86/Paris_Saint-Germain_Logo.svg/1200px-Paris_Saint-Germain_Logo.svg.png",
    "name2": "PSG",
    "champ": "LDC",
    "heure": "19H00",
    "date": "29/04/2025",
    "pro": "But avant 30 Min (NON)"
  },  
  {
    "photo1": "https://upload.wikimedia.org/wikipedia/commons/thumb/5/55/Al_Hilal_SFC_Logo.svg/1200px-Al_Hilal_SFC_Logo.svg.png",
    "name1": "Al-Hilal",
    "photo2": "https://upload.wikimedia.org/wikipedia/fr/thumb/4/45/Al_Ahli_Saudi_FC_logo.svg/1200px-Al_Ahli_Saudi_FC_logo.svg.png",
    "name2": "Al-Ahli",
    "champ": "AFC Elitr Ligue",
    "heure": "16H30",
    "date": "29/04/2025",
    "pro": "Au moins une EQuipe marque (1.5)"
  },
  {
    "photo1": "https://upload.wikimedia.org/wikipedia/fr/thumb/b/b3/FK_Jelgava_Logo.svg/1200px-FK_Jelgava_Logo.svg.png",
    "name1": "Jelgava",
    "photo2": "https://upload.wikimedia.org/wikipedia/lv/b/b5/Grobinas_SC_LFS_logo.png",
    "name2": "Grobina",
    "champ": "Lettonie Championnat",
    "heure": "16H00",
    "date": "29/04/2025",
    "pro": "Total 1 (1.5)"
    },
    {
    "photo1": "https://upload.wikimedia.org/wikipedia/fr/thumb/e/ed/Logo_UD_Almer%C3%ADa.svg/1200px-Logo_UD_Almer%C3%ADa.svg.png",
    "name1": "Almeria",
    "photo2": "https://upload.wikimedia.org/wikipedia/commons/4/4c/Escudo_rcf.png",
    "name2": "Racin de Ferrol",
    "champ": "Espagne D2",
    "heure": "18H30",
    "date": "29/04/2025",
    "pro": "V1"
  },
  {
    "photo1": "https://upload.wikimedia.org/wikipedia/fr/thumb/1/17/Logo_Malm%C3%B6_FF.svg/1200px-Logo_Malm%C3%B6_FF.svg.png",
    "name1": "Malmo",
    "photo2": "https://upload.wikimedia.org/wikipedia/fr/thumb/4/4a/Osters_IF.svg/1200px-Osters_IF.svg.png",
    "name2": "Osters",
    "champ": "Eerste Divisie",
    "heure": "17H00",
    "date": "29/04/2025",
    "pro": "V1"
  },
  {
    "photo1": "https://upload.wikimedia.org/wikipedia/en/thumb/5/53/Burton_Albion_FC_logo.svg/1200px-Burton_Albion_FC_logo.svg.png",
    "name1": "Burton Albion",
    "photo2": "https://upload.wikimedia.org/wikipedia/fr/thumb/c/cc/Logo_Wigan_Athletic.svg/1200px-Logo_Wigan_Athletic.svg.png",
    "name2": "Wigan Athletic",
    "champ": "Angleterre Ligue 1",
    "heure": "18H45",
    "date": "29/04/2025",
    "pro": "2X"
  }
]


