[
   {
    "photo1": "https://upload.wikimedia.org/wikipedia/en/thumb/c/ce/Valenciacf.svg/953px-Valenciacf.svg.png",
    "name1": "Valencia",
    "photo2": "https://upload.wikimedia.org/wikipedia/en/thumb/9/98/Club_Athletic_Bilbao_logo.svg/1059px-Club_Athletic_Bilbao_logo.svg.png",
    "name2": "Athletic Bilbao",
    "champ": "Espagne. LaLiga",
    "heure": "19H00",
    "date": "20/09/2025",
    "pro": "2X"
  },  
  {
    "photo1": "https://encrypted-tbn0.gstatic.com/images?q=tbn:ANd9GcQD_vQ6rGBPxg9WMjAvvXvpWp15b-V9qrkBGA&s",
    "name1": "Hellas Verona",
    "photo2": "https://upload.wikimedia.org/wikipedia/commons/5/51/Juventus_FC_2017_logo.png",
    "name2": "Juventus",
    "champ": "Italie. Série A",
    "heure": "16H00",
    "date": "20/09/2025",
    "pro": "Total: (+1.5)"
  },
  {
    "photo1": "https://upload.wikimedia.org/wikipedia/en/thumb/c/ce/Udinese_Calcio_logo.svg/1200px-Udinese_Calcio_logo.svg.png",
    "name1": "Udinese Calcio",
    "photo2": "https://upload.wikimedia.org/wikipedia/commons/thumb/d/d0/Logo_of_AC_Milan.svg/langfr-250px-Logo_of_AC_Milan.svg.png",
    "name2": "Milan",
    "champ": "Italie. Série A",
    "heure": "18H45",
    "date": "20/09/2025",
    "pro": "12"
    },
    {
    "photo1": "https://encrypted-tbn0.gstatic.com/images?q=tbn:ANd9GcRjmqcrc22QHUDF3zA9sew2vhEExe0wCknNsg&s",
    "name1": "Dynamo Makhachkala",
    "photo2": "https://e7.pngegg.com/pngimages/677/837/png-clipart-lokomotiv-stadium-fc-lokomotiv-moscow-russian-premier-league-pfc-cska-moscow-fc-dynamo-moscow-football-text-team-thumbnail.png",
    "name2": "Lokomotiv Moscou",
    "champ": "Russie. Première Ligue",
    "heure": "16H30",
    "date": "20/09/2025",
    "pro": "2X"
  },
  {
    "photo1": "https://encrypted-tbn0.gstatic.com/images?q=tbn:ANd9GcR5IWIYXgSpdXNRK_ZEyy0KYf8jNci_lnrk3Q&s",
    "name1": "Stade Brestois",
    "photo2": "https://upload.wikimedia.org/wikipedia/fr/thumb/b/b1/Logo_OGC_Nice_2013.svg/1644px-Logo_OGC_Nice_2013.svg.png",
    "name2": "Nice",
    "champ": "France. Ligue 1",
    "heure": "17H00",
    "date": "20/09/2025",
    "pro": "Total: (+1.5)"
  },
  {
    "photo1": "https://upload.wikimedia.org/wikipedia/fr/thumb/c/c5/Logo_RC_Lens.svg/755px-Logo_RC_Lens.svg.png",
    "name1": "RC Lens",
    "photo2": "https://upload.wikimedia.org/wikipedia/fr/thumb/6/62/Logo_LOSC_Lille_2018.svg/1200px-Logo_LOSC_Lille_2018.svg.png",
    "name2": "Lille OSC",
    "champ": "France. Ligue 2",
    "heure": "19H05",
    "date": "20/09/2025",
    "pro": "12"
  }
]


