   
[
  {
    "photo1": "https://encrypted-tbn0.gstatic.com/images?q=tbn:ANd9GcR8zhzvanjuDSHVRF80UuY7C-aZB-zp-Sx1lA&s",
    "name1": "Tommy Paul",
    "photo2": "https://encrypted-tbn0.gstatic.com/images?q=tbn:ANd9GcR3kjGOPQxcWNLFI0aAo6D-XCR4xNb995_4uQ&s",
    "name2": "Luciano Darderi",
    "champ": "Tennis. ATP. Rome",
    "heure": "15H30",
    "date": "10/05/2026",
    "pro": "Total: (+18.5)"
  },  
  {
    "photo1": "https://encrypted-tbn0.gstatic.com/images?q=tbn:ANd9GcRNod00Ysm5oP2dKTWmsmfKBOB_039Le_LLuQ&s",
    "name1": "Matteo Arnaldi",
    "photo2": "https://upload.wikimedia.org/wikipedia/commons/thumb/8/8c/Rafa_J%C3%B3dar_Espinar_2025.jpg/250px-Rafa_J%C3%B3dar_Espinar_2025.jpg",
    "name2": "Raphael Jodar",
    "champ": "Tennis. ATP. Rome",
    "heure": "18H30",
    "date": "10/05/2026",
    "pro": "Handicap: 1(6.5)" 
  },
  {
    "photo1": "https://encrypted-tbn0.gstatic.com/images?q=tbn:ANd9GcSLpMGo1-Fn89ro0_a61SZc6zc-p4B32_K-Lg&s",
    "name1": "Laura Siegemund",
    "photo2": "https://upload.wikimedia.org/wikipedia/commons/thumb/4/45/Aegon_International_Women%27s_Final_2017_Pliscova_v_Wozniacki-411_%2835754557585%29.jpg/250px-Aegon_International_Women%27s_Final_2017_Pliscova_v_Wozniacki-411_%2835754557585%29.jpg",
    "name2": "Karolina Pliskova",
    "champ": "Tennis. WTA. Rome",
    "heure": "17H00",
    "date": "10/05/2026",
    "pro": "Total: (+19)"
  },
    {
    "photo1": "https://upload.wikimedia.org/wikipedia/commons/a/a4/Cocciaretto_RGQ22_%2819%29_%2852130125890%29.jpg",
    "name1": "Elisabetta Cocciaretto",
    "photo2": "https://encrypted-tbn0.gstatic.com/images?q=tbn:ANd9GcT7__7zByKsowCKYfokTYqmN7CndOTiIa37Pg&s",
    "name2": "Iga Swiatek",
    "champ": "Tennis. WTA. Rome",
    "heure": "17H00",
    "date": "10/05/2026",
    "pro": "1X2: V2"
  },
  {
    "photo1": "https://encrypted-tbn0.gstatic.com/images?q=tbn:ANd9GcSoFtYXH37lEvGsvJ1aruIxU3NDbOw9cjHwyA&s",
    "name1": "Agustin Libre",
    "photo2": "https://images.sidearmdev.com/convert?url=https%3A%2F%2Fdxbhsrqyrr690.cloudfront.net%2Fsidearm.nextgen.sites%2Fathletics.uindy.edu%2Fimages%2F2016%2F5%2F8%2Fwebarklon.jpg&type=webp",
    "name2": "Arklon Huertas Del Pino Cordova",
    "champ": "Tennis. Challenger. Cordoba",
    "heure": "16H00",
    "date": "10/05/2026",
    "pro": "1X2: V2"
  },
    {
    "photo1": "https://encrypted-tbn0.gstatic.com/images?q=tbn:ANd9GcT-Z6G5zGqU5hlOkIVrfmIcOGmzvze1Z_23Gg&s",
    "name1": "Leonel Cesar Castro",
    "photo2": "https://encrypted-tbn0.gstatic.com/images?q=tbn:ANd9GcR8S_d0nNzAa0zUV7ekMEDDPqu2jxbh0IVCAQ&s",
    "name2": "Lautaro Agustin Falabella",
    "champ": "Tennis. Challenger. Cordoba",
    "heure": "16H00",
    "date": "10/05/2026",
    "pro": "1X2: V2"
  },
  {
    "photo1": "https://encrypted-tbn0.gstatic.com/images?q=tbn:ANd9GcQlTv9m9yDbbEU4zyHZLhsWrYqzhell4Oj79A&s",
    "name1": "Alexandra Eala",
    "photo2": "https://encrypted-tbn0.gstatic.com/images?q=tbn:ANd9GcR8iSSHVSDgML4XDV8J3wYZEScf1c_qHe6Dvg&s",
    "name2": "Elena Rybakina",
    "champ": "Tennis. WTA. Rome",
    "heure": "14H00",
    "date": "10/05/2026",
    "pro": "Total: (+16.5)"
  },
    {
    "photo1": "https://encrypted-tbn0.gstatic.com/images?q=tbn:ANd9GcTNJxBHEX4neNxjaj4WrDeo3x8bFrho8zFAbQ&s",
    "name1": "Lorenzo Musetti",
    "photo2": "https://encrypted-tbn0.gstatic.com/images?q=tbn:ANd9GcShBc7_61-Pr9-DcYTZHQ953c2iAOtkwohGRg&s",
    "name2": "Francisco Cerundolo",
    "champ": "Tennis. ATP. Rome",
    "heure": "13H00",
    "date": "10/05/2026",
    "pro": "Total: (+20.5)"
  },
  {
    "photo1": "https://encrypted-tbn0.gstatic.com/images?q=tbn:ANd9GcTxDbUB3w21BMgATp8YlNf-nDYOffXgeszjfA&s",
    "name1": "Learner Tien",
    "photo2": "https://upload.wikimedia.org/wikipedia/commons/thumb/c/c7/Sascha_Bublik_%282023_DC_Open%29_05_%28cropped%29.jpg/250px-Sascha_Bublik_%282023_DC_Open%29_05_%28cropped%29.jpg",
    "name2": "Alexander Bublik",
    "champ": "Tennis. ATP. Rome",
    "heure": "13H30",
    "date": "10/05/2026",
    "pro": "Total: (+20)"
  },
  {
    "photo1": "https://encrypted-tbn0.gstatic.com/images?q=tbn:ANd9GcSpVWzIbiLCc9LGP86CiBS4ZNjW4aOau2K0sw&s",
    "name1": "Naomi Osaka",
    "photo2": "https://upload.wikimedia.org/wikipedia/commons/thumb/7/7a/Diana_Shnaider_%28Roland_Garros_2023%29_03_%28cropped%29.jpg/330px-Diana_Shnaider_%28Roland_Garros_2023%29_03_%28cropped%29.jpg",
    "name2": "Diana Shnaider",
    "champ": "Tennis. WTA. Rome",
    "heure": "12H30",
    "date": "10/05/2026",
    "pro": "Total: (+18.5)"
  }
]
