
[
  {
    "photo1": "https://encrypted-tbn0.gstatic.com/images?q=tbn:ANd9GcSVwOQtqGcU0q65NN2cshsMBuUWv52zAjoLkQ&s",
    "name1": "Arthur Fery",
    "photo2": "https://upload.wikimedia.org/wikipedia/commons/5/53/Cobolli_RGQ23_%2852944096963%29.jpg",
    "name2": "Flavio Cobolli",
    "champ": "Tennis. Open d'Australie",
    "heure": "00H00",
    "date": "18/01/2026",
    "pro": "Total: (+35.5)"
  },  
  {
    "photo1": "https://upload.wikimedia.org/wikipedia/commons/0/0e/Kecmanovic_RG21_%2811%29_%2851377164760%29.jpg",
    "name1": "Miomir Kecmanovic",
    "photo2": "https://encrypted-tbn0.gstatic.com/images?q=tbn:ANd9GcQvO-fD7RaIbbTOdvpyh8rjQhB90J0MIkZDyA&s",
    "name2": "Tomas Martin Etcheverry",
    "champ": "Tennis. Open d'Australie",
    "heure": "00H00",
    "date": "18/01/2026",
    "pro": "Total: (+36.5)"
  },
  {
    "photo1": "https://upload.wikimedia.org/wikipedia/commons/thumb/7/78/Tristan_Schoolkate_%282024_DC_Open%29_01.jpg/330px-Tristan_Schoolkate_%282024_DC_Open%29_01.jpg",
    "name1": "Tristan Schoolkate",
    "photo2": "https://encrypted-tbn0.gstatic.com/images?q=tbn:ANd9GcQuEkTARIklg4JiMm38B8slLjff4hBlDUa0MQ&s",
    "name2": "Corentin Moutet",
    "champ": "Tennis. Open d'Australie",
    "heure": "01H30",
    "date": "18/01/2026",
    "pro": "V2"
  },
    {
    "photo1": "https://upload.wikimedia.org/wikipedia/commons/thumb/7/78/Khachanov_MCM22_%2814%29_%2852036660479%29.jpg/250px-Khachanov_MCM22_%2814%29_%2852036660479%29.jpg",
    "name1": "Emilio Nava",
    "photo2": "https://upload.wikimedia.org/wikipedia/commons/thumb/4/45/Jacquet_MLC22.jpg/250px-Jacquet_MLC22.jpg",
    "name2": "Kyrian Jacquet",
    "champ": "Tennis. Open d'Australie",
    "heure": "01H30",
    "date": "18/01/2026",
    "pro": "Total: (+36.5)"
  },
  {
    "photo1": "https://encrypted-tbn0.gstatic.com/images?q=tbn:ANd9GcSICchRjPWWG73kfFGH4vQf4XvvMVpk-tuINg&s",
    "name1": "Alexander Zverev",
    "photo2": "https://encrypted-tbn0.gstatic.com/images?q=tbn:ANd9GcRZg0bj2JsNYsl7fVuGdt9Z8ZaTPxUpV-Jk_g&s",
    "name2": "Gabriel Diallo",
    "champ": "Tennis. Open d'Australie",
    "heure": "02H00",
    "date": "18/01/2026",
    "pro": "Total: (+32.5)"
  },
  {
    "photo1": "https://encrypted-tbn0.gstatic.com/images?q=tbn:ANd9GcShBc7_61-Pr9-DcYTZHQ953c2iAOtkwohGRg&s",
    "name1": "Francisco Cerundolo",
    "photo2": "https://encrypted-tbn0.gstatic.com/images?q=tbn:ANd9GcQSQepiFlSVWzvqDWm3jEATOsqq_GtWZMKnCw&s",
    "name2": "Zhizhen Zhang",
    "champ": "Tennis. Open d'Australie",
    "heure": "02H00",
    "date": "18/01/2026",
    "pro": "Total: (+35.5)"
  }
]
